map_parallel/__init__.py
map_parallel-0.2.0.dist-info/AUTHORS.rst
map_parallel-0.2.0.dist-info/LICENSE
map_parallel-0.2.0.dist-info/METADATA
map_parallel-0.2.0.dist-info/WHEEL
map_parallel-0.2.0.dist-info/top_level.txt
map_parallel-0.2.0.dist-info/RECORD
